Package1ByShazma/__init__.py
Package1ByShazma/module1ByShazma.py
Package1ByShazma/module3ByShazma.py
Package2ByShazma/__init__.py
Package2ByShazma/module2ByShazma.py
LibraryByShazma-0.1.dist-info/LICENCE.txt
LibraryByShazma-0.1.dist-info/METADATA
LibraryByShazma-0.1.dist-info/WHEEL
LibraryByShazma-0.1.dist-info/top_level.txt
LibraryByShazma-0.1.dist-info/RECORD
