Metadata-Version: 2.1
Name: LibraryByShazma
Version: 0.1
Summary: Having modules with Basic calculator, Sorting and Searching algorithms.
Author: Shazma Noor
Author-email: phddsf22m004@pucit.edu.pk
Classifier: Programming Language :: Python :: 3
Classifier: License :: OSI Approved :: MIT License
Classifier: Operating System :: OS Independent
License-File: LICENCE.txt
